munkres.py
munkres-1.1.2.dist-info/LICENSE.md
munkres-1.1.2.dist-info/METADATA
munkres-1.1.2.dist-info/WHEEL
munkres-1.1.2.dist-info/top_level.txt
munkres-1.1.2.dist-info/RECORD
